gdtoolkit/__init__.py
gdtoolkit/common/__init__.py
gdtoolkit/common/ast.py
gdtoolkit/common/exceptions.py
gdtoolkit/common/types.py
gdtoolkit/common/utils.py
gdtoolkit/formatter/__init__.py
gdtoolkit/formatter/__main__.py
gdtoolkit/formatter/annotation.py
gdtoolkit/formatter/block.py
gdtoolkit/formatter/class_statement.py
gdtoolkit/formatter/comments.py
gdtoolkit/formatter/const_statement.py
gdtoolkit/formatter/constants.py
gdtoolkit/formatter/context.py
gdtoolkit/formatter/exceptions.py
gdtoolkit/formatter/expression.py
gdtoolkit/formatter/expression_to_str.py
gdtoolkit/formatter/expression_utils.py
gdtoolkit/formatter/formatter.py
gdtoolkit/formatter/function_statement.py
gdtoolkit/formatter/function_statement_to_str.py
gdtoolkit/formatter/property.py
gdtoolkit/formatter/safety_checks.py
gdtoolkit/formatter/statement_utils.py
gdtoolkit/formatter/types.py
gdtoolkit/formatter/var_statement.py
gdtoolkit/gd2py/__init__.py
gdtoolkit/gd2py/__main__.py
gdtoolkit/gdradon/__init__.py
gdtoolkit/gdradon/__main__.py
gdtoolkit/linter/__init__.py
gdtoolkit/linter/__main__.py
gdtoolkit/linter/basic_checks.py
gdtoolkit/linter/class_checks.py
gdtoolkit/linter/design_checks.py
gdtoolkit/linter/format_checks.py
gdtoolkit/linter/helpers.py
gdtoolkit/linter/if_return_checks.py
gdtoolkit/linter/misc_checks.py
gdtoolkit/linter/name_checks.py
gdtoolkit/linter/problem.py
gdtoolkit/linter/problem_printer.py
gdtoolkit/linter/types.py
gdtoolkit/parser/__init__.py
gdtoolkit/parser/__main__.py
gdtoolkit/parser/comments.lark
gdtoolkit/parser/gdscript.lark
gdtoolkit/parser/gdscript_indenter.py
gdtoolkit/parser/parser.py
gdtoolkit-4.5.0.dist-info/LICENSE
gdtoolkit-4.5.0.dist-info/METADATA
gdtoolkit-4.5.0.dist-info/WHEEL
gdtoolkit-4.5.0.dist-info/entry_points.txt
gdtoolkit-4.5.0.dist-info/top_level.txt
gdtoolkit-4.5.0.dist-info/RECORD
