Metadata-Version: 2.1
Name: gdtoolkit
Version: 4.5.0
Summary: Independent set of tools for working with GDScript - parser, linter and formatter
Home-page: https://github.com/Scony/godot-gdscript-toolkit
Author: Pawel Lampe
Author-email: pawel.lampe@gmail.com
License: MIT
Keywords: GODOT,GDSCRIPT,PARSER,LINTER,FORMATTER
Classifier: Development Status :: 5 - Production/Stable
Classifier: Intended Audience :: Developers
Classifier: License :: OSI Approved :: MIT License
Classifier: Programming Language :: Python :: 3
Classifier: Programming Language :: Python :: 3.7
Classifier: Programming Language :: Python :: 3.8
Classifier: Programming Language :: Python :: 3.9
Classifier: Programming Language :: Python :: 3.10
Classifier: Topic :: Software Development :: Libraries :: Python Modules
Requires-Python: >=3.7
License-File: LICENSE
Requires-Dist: lark[regex]==1.2.2
Requires-Dist: docopt-ng==0.9.0
Requires-Dist: pyyaml>=5.1
Requires-Dist: radon==6.0.1
Requires-Dist: setuptools
